{"stat.useItem.minecraft.string":1,"stat.mineBlock.extratrees.leaves.default.19":4,"stat.leaveGame":9,"stat.pickup.tconstruct.edible":12,"stat.drop.tconstruct.pickaxe":3,"stat.mineBlock.immersiveengineering.ore":67,"stat.useItem.thermalfoundation.ore":1,"stat.useItem.harvestcraft.pearitem":24,"stat.drop.minecraft.iron_sword":3,"stat.pickup.minecraft.rotten_flesh":123,"stat.pickup.minecraft.sand":2,"stat.entityKilledBy.Spider":1,"stat.useItem.harvestcraft.walnutitem":68,"stat.killEntity.Enderman":1,"stat.mineBlock.extratrees.leaves.default.2":1,"stat.useItem.extratrees.food":104,"stat.useItem.minecraft.brown_mushroom":3,"stat.pickup.minecraft.brown_mushroom":4,"stat.mineBlock.minecraft.sand":1,"stat.mineBlock.extratrees.leaves.default.21":8,"stat.mineBlock.extratrees.leaves.default.20":10,"stat.mineBlock.openblocks.grave":15,"stat.useItem.minecraft.iron_pickaxe":2393,"stat.drop.minecraft.diamond":5,"stat.craftItem.minecraft.wooden_pickaxe":2,"stat.pickup.valkyrielib.guide":1,"stat.pickup.minecraft.double_plant":6,"stat.pickup.bqt.bqbook":1,"stat.mineBlock.chisel.marble2":455,"stat.furnaceInteraction":4,"stat.pickup.harvestcraft.cherryitem":70,"stat.pickup.harvestcraft.barleyseeditem":1,"stat.pickup.minecraft.iron_chestplate":13,"stat.pickup.spiceoflife.lunchbox":3,"stat.mineBlock.minecraft.fence":1,"stat.pickup.techreborn.gem":32,"stat.pickup.harvestcraft.nutmegitem":43,"stat.useItem.natura.edibles":34,"stat.deaths":17,"stat.pickup.minecraft.egg":55,"stat.playOneMinute":1101059,"stat.mineBlock.actuallyadditions.block_wild":8,"stat.mineBlock.harvestcraft.pamchestnut":22,"stat.pickup.chisel.marble2":452,"stat.mineBlock.minecraft.tallgrass":34,"stat.chestOpened":88,"stat.pickup.minecraft.pumpkin":9,"stat.useItem.minecraft.stone":9,"stat.pickup.minecraft.iron_sword":23,"stat.pickup.minecraft.arrow":98,"stat.mineBlock.appliedenergistics2.charged_quartz_ore":5,"stat.pickup.harvestcraft.tomatoseeditem":1,"stat.mineBlock.natura.overworld_berrybush_blueberry":12,"stat.fallOneCm":130159,"stat.mineBlock.harvestcraft.pamhazelnut":27,"stat.crouchOneCm":4920,"stat.mineBlock.minecraft.chest":1,"stat.pickup.actuallyadditions.item_food":8,"stat.craftItem.minecraft.iron_ingot":6,"stat.pickup.harvestcraft.walnutitem":91,"stat.mineBlock.harvestcraft.pamlemon":1,"stat.pickup.techreborn.ore":78,"stat.mineBlock.harvestcraft.pamnutmeg":13,"stat.pickup.natura.edibles":34,"stat.pickup.minecraft.wooden_pickaxe":2,"stat.mineBlock.harvestcraft.pamcherry":30,"stat.pickup.minecraft.dye":165,"stat.pickup.minecraft.planks":7,"stat.pickup.minecraft.iron_leggings":10,"stat.pickup.chisel.limestone2":13,"stat.pickup.minecraft.wheat_seeds":9,"stat.mineBlock.minecraft.gravel":118,"stat.useItem.minecraft.stone_pickaxe":121,"stat.useItem.harvestcraft.cherryitem":46,"stat.mineBlock.minecraft.dirt":209,"stat.pickup.harvestcraft.strawberryseeditem":1,"stat.useItem.minecraft.torch":442,"stat.mineBlock.actuallyadditions.block_black_lotus":1,"stat.useItem.minecraft.cobblestone":120,"stat.pickup.natura.overworld_berrybush_raspberry":12,"stat.mineBlock.extratrees.leaves.default.fruit.12":13,"stat.pickup.extratrees.food":70,"stat.mineBlock.extratrees.leaves.default.fruit.11":12,"stat.mineBlock.extratrees.leaves.default.fruit.10":13,"stat.pickup.tconstruct.pickaxe":10,"stat.mineBlock.quark.stone_speleothem":21,"stat.pickup.harvestcraft.chilipepperseeditem":2,"stat.mineBlock.harvestcraft.pamgooseberry":22,"stat.pickup.minecraft.log":15,"stat.pickup.harvestcraft.hazelnutitem":96,"stat.pickup.minecraft.iron_pickaxe":19,"stat.useItem.tconstruct.pickaxe":2891,"stat.pickup.minecraft.sapling":8,"stat.entityKilledBy.Enderman":1,"stat.pickup.minecraft.apple":146,"stat.pickup.harvestcraft.parsnipitem":4,"stat.pickup.tconstruct.broadsword":9,"stat.craftItem.minecraft.planks":38,"stat.useItem.minecraft.iron_sword":612,"stat.pickup.fluxnetworks.flux":5,"stat.mineBlock.minecraft.log":10,"stat.pickup.harvestcraft.garlicseeditem":1,"stat.pickup.harvestcraft.pearitem":30,"stat.sneakTime":869,"stat.pickup.minecraft.wool":10,"stat.pickup.harvestcraft.avocadoitem":2,"stat.pickup.minecraft.chest":1,"stat.pickup.harvestcraft.gooseberryitem":73,"stat.pickup.immersiveengineering.ore":94,"stat.pickup.minecraft.bone":79,"stat.pickup.forestry.sapling":4,"stat.horseOneCm":6884,"stat.mineBlock.minecraft.cobblestone":12,"stat.mineBlock.minecraft.pumpkin":3,"stat.pickup.minecraft.stone_pickaxe":3,"stat.pickup.minecraft.flint":25,"stat.useItem.harvestcraft.hazelnutitem":54,"stat.mineBlock.minecraft.brown_mushroom":6,"stat.mineBlock.appliedenergistics2.quartz_ore":60,"stat.swimOneCm":217441,"stat.climbOneCm":1504,"stat.mineBlock.harvestcraft.pamsoursop":4,"stat.useItem.minecraft.dirt":40,"stat.useItem.minecraft.stone_slab2":28,"stat.pickup.minecraft.bow":8,"stat.pickup.minecraft.iron_boots":9,"stat.useItem.harvestcraft.gooseberryitem":42,"stat.pickup.thermalfoundation.ore":814,"stat.useItem.minecraft.egg":6,"stat.mineBlock.minecraft.obsidian":8,"stat.pickup.minecraft.cobblestone":1868,"stat.mineBlock.minecraft.clay":7,"stat.mineBlock.chisel.limestone2":13,"stat.flyOneCm":260175,"stat.pickup.appliedenergistics2.material":156,"stat.pickup.actuallyadditions.item_booklet":1,"stat.useItem.harvestcraft.plumitem":6,"stat.pickup.minecraft.redstone":237,"stat.mineBlock.minecraft.iron_ore":936,"stat.useItem.tconstruct.broadsword":72,"stat.timeSinceDeath":291398,"stat.pickup.harvestcraft.mustardseeditem":1,"stat.pickup.minecraft.mutton":14,"stat.pickup.actuallyadditions.item_rice_seed":10,"stat.pickup.minecraft.mossy_cobblestone":2,"stat.pickup.harvestcraft.soursopitem":17,"stat.useItem.harvestcraft.soursopitem":17,"stat.mineBlock.thermalfoundation.ore":651,"stat.mineBlock.minecraft.coal_ore":2004,"stat.killEntity.Creeper":7,"stat.pickup.extrautils2.ingredients":5,"stat.pickup.minecraft.string":31,"stat.pickup.harvestcraft.blackberryseeditem":1,"stat.entityKilledBy.Skeleton":6,"stat.pickup.natura.overworld_berrybush_blueberry":15,"stat.sprintOneCm":1588010,"stat.pickup.actuallyadditions.item_misc":1,"stat.craftItem.minecraft.stick":107,"stat.mineBlock.harvestcraft.pamwalnut":32,"stat.pickup.harvestcraft.peanutseeditem":2,"stat.mineBlock.minecraft.diamond_ore":5,"stat.mineBlock.harvestcraft.pamapple":41,"stat.useItem.minecraft.diamond_pickaxe":1089,"stat.entityKilledBy.Creeper":3,"stat.drop":14,"stat.craftItem.actuallyadditions.item_misc":16,"stat.killEntity.Sheep":6,"stat.pickup.minecraft.slime_ball":2,"stat.killEntity.Zombie":69,"stat.mineBlock.forestry.leaves.default.0":1,"stat.mineBlock.minecraft.gold_ore":74,"stat.diveOneCm":37457,"stat.mineBlock.minecraft.mossy_cobblestone":1,"stat.useItem.harvestcraft.rainbowcurryitem":3,"stat.mineBlock.traverse.fir_leaves":3,"stat.drop.minecraft.wooden_pickaxe":1,"stat.pickup.minecraft.gravel":179,"stat.useItem.harvestcraft.nutmegitem":33,"stat.useItem.minecraft.apple":93,"stat.drop.minecraft.apple":1,"stat.jump":12233,"stat.pickup.minecraft.fence":2,"stat.pickup.minecraft.coal":2552,"stat.pickup.minecraft.iron_helmet":8,"stat.pickup.minecraft.iron_ingot":3,"stat.pickup.actuallyadditions.block_black_lotus":1,"stat.pickup.minecraft.gunpowder":17,"stat.pickup.minecraft.spider_eye":2,"stat.craftItem.minecraft.torch":590,"stat.pickup.minecraft.dirt":305,"stat.useItem.minecraft.cooked_chicken":1,"stat.pickup.harvestcraft.chestnutitem":82,"stat.pickup.minecraft.iron_ore":1224,"stat.pickup.minecraft.gold_ore":113,"stat.useItem.minecraft.sapling":1,"stat.mineBlock.minecraft.lapis_ore":15,"stat.pickup.actuallyadditions.item_coffee_seed":13,"stat.damageTaken":11909,"stat.mineBlock.minecraft.torch":10,"stat.killEntity.tconstruct.blueslime":15,"stat.useItem.minecraft.wooden_pickaxe":3,"stat.pickup.harvestcraft.pawpawitem":39,"stat.mineBlock.harvestcraft.pamavocado":1,"stat.useItem.forestry.scoop":6,"stat.mineBlock.harvestcraft.pamplum":10,"stat.killEntity.CaveSpider":1,"stat.pickup.harvestcraft.whitemushroomseeditem":1,"stat.pickup.harvestcraft.leekseeditem":2,"stat.entityKilledBy.Zombie":3,"stat.damageDealt":30266,"stat.pickup.harvestcraft.rainbowcurryitem":3,"stat.sleepInBed":7,"stat.useItem.harvestcraft.chestnutitem":42,"stat.mineBlock.harvestcraft.pamspiderweb":6,"stat.mineBlock.harvestcraft.pampear":19,"stat.walkOneCm":5009145,"stat.pickup.minecraft.stick":94,"stat.pickup.minecraft.diamond_pickaxe":4,"stat.pickup.minecraft.clay_ball":66,"stat.pickup.actuallyadditions.item_bag":3,"stat.useItem.harvestcraft.pawpawitem":15,"stat.mineBlock.harvestcraft.pampawpaw":12,"stat.mineBlock.natura.overworld_berrybush_raspberry":12,"stat.mineBlock.techreborn.ore":74,"stat.mineBlock.quark.granite_speleothem":1,"stat.drop.minecraft.iron_chestplate":1,"stat.pickup.minecraft.stone":193,"stat.pickup.harvestcraft.onionseeditem":2,"stat.pickup.actuallyadditions.item_coffee_beans":21,"stat.killEntity.Skeleton":49,"stat.pickup.forestry.apatite":256,"stat.pickup.forestry.scoop":1,"stat.useItem.harvestcraft.parsnipitem":4,"stat.useItem.harvestcraft.strawberryjuiceitem":9,"stat.killEntity.Spider":10,"stat.useItem.harvestcraft.avocadoitem":2,"stat.mineBlock.forestry.resources":68,"stat.mobKills":158,"stat.pickup.harvestcraft.plumitem":21,"stat.pickup.harvestcraft.zucchiniseeditem":2,"stat.pickup.minecraft.diamond":6,"stat.mineBlock.minecraft.leaves":65,"stat.pickup.minecraft.torch":812,"stat.mineBlock.minecraft.redstone_ore":52,"stat.pickup.harvestcraft.strawberryjuiceitem":12,"stat.useItem.spiceoflife.lunchbox":1,"stat.mineBlock.harvestcraft.pampapaya":1,"stat.mineBlock.minecraft.stone":1618}